knn_torch/__init__.py
knn_torch/knn.py
knn_torch-0.1.1.dist-info/LICENSE
knn_torch-0.1.1.dist-info/METADATA
knn_torch-0.1.1.dist-info/WHEEL
knn_torch-0.1.1.dist-info/RECORD
