Metadata-Version: 2.1
Name: knn-torch
Version: 0.1.1
Summary: 
Author: Yeok-c
Author-email: yeokch@gmail.com
Requires-Python: >=3.9,<3.13
Classifier: Programming Language :: Python :: 3
Classifier: Programming Language :: Python :: 3.9
Classifier: Programming Language :: Python :: 3.10
Classifier: Programming Language :: Python :: 3.11
Classifier: Programming Language :: Python :: 3.12
Requires-Dist: matplotlib (>=3.9.2,<4.0.0)
Requires-Dist: torch (>=2.0.0,<3.0.0)
